rukip/__init__.py
rukip/featurizer/__init__.py
rukip/featurizer/ckip_featurizer.py
rukip/featurizer/test_ckipfeatureizer.py
rukip/tokenizer/__init__.py
rukip/tokenizer/ckip_tokenizer.py
rukip/tokenizer/test_ckiptokenizer.py
rukip-0.0.6.dist-info/LICENSE
rukip-0.0.6.dist-info/METADATA
rukip-0.0.6.dist-info/WHEEL
rukip-0.0.6.dist-info/top_level.txt
rukip-0.0.6.dist-info/RECORD
