Metadata-Version: 2.1
Name: rukip
Version: 0.0.6
Summary: An Embedded CKIP Rasa NLU Components
Home-page: https://github.com/circlelychen/rukip
Author: Hao-Yuan Chen
Author-email: truecirclely@gmail.com
License: UNKNOWN
Platform: UNKNOWN
Classifier: Programming Language :: Python :: 3
Classifier: License :: OSI Approved :: GNU General Public License v3 (GPLv3)
Classifier: Operating System :: OS Independent
Requires-Python: >=3.6
Requires-Dist: rasa (<1.7,>=1.4.0)
Requires-Dist: ckiptagger[tf] (>=0.0.19)
